henry/__init__.py
henry/__version__.py
henry/cli.py
henry/.support_files/help.rtf
henry/commands/__init__.py
henry/commands/analyze.py
henry/commands/pulse.py
henry/commands/vacuum.py
henry/modules/__init__.py
henry/modules/exceptions.py
henry/modules/fetcher.py
henry/modules/spinner.py
henry_temp_fix-1.1.2.data/data/henry/.support_files/help.rtf
henry_temp_fix-1.1.2.dist-info/LICENSE.txt
henry_temp_fix-1.1.2.dist-info/METADATA
henry_temp_fix-1.1.2.dist-info/WHEEL
henry_temp_fix-1.1.2.dist-info/entry_points.txt
henry_temp_fix-1.1.2.dist-info/top_level.txt
henry_temp_fix-1.1.2.dist-info/RECORD
