Metadata-Version: 2.1
Name: henry-temp-fix
Version: 1.1.2
Summary: A Looker Cleanup Tool
Home-page: https://pypi.python.org/pypi/henry
Author: Joseph Axisa
Author-email: jax@looker.com
License: MIT
Keywords: Looker Cleanup,Looker Henry,Henry
Platform: UNKNOWN
Requires-Python: >=3.7.0
License-File: LICENSE.txt
Requires-Dist: looker-sdk>=21
Requires-Dist: tabulate
